formpix/__init__.py
formpix/client.py
formpix-1.0.3.dist-info/METADATA
formpix-1.0.3.dist-info/WHEEL
formpix-1.0.3.dist-info/top_level.txt
formpix-1.0.3.dist-info/RECORD
